.gitattributes
.gitignore
.pylintrc
.readthedocs.yml
LICENSE.txt
LICENSE_SHORT
MANIFEST.in
README.md
pytest.ini
setup.cfg
setup.py
spawn.ini
tox.ini
versioneer.py
.circleci/config.yml
docs/conf.py
docs/generate.py
docs/index.rst
docs/user_guide/getting_started.md
docs/user_guide/ini_guide.md
example_data/Discon.dll
example_data/FASTv7.0.2.exe
example_data/TurbSim.exe
example_data/dlc_spec.json
example_data/iec_fatigue_spec.json
example_data/iec_fatigue_spec_starter.json
example_data/iec_spec.json
example_data/fast_input_files/NRELOffshrBsline5MW_ADAMSSpecific.dat
example_data/fast_input_files/NRELOffshrBsline5MW_AeroDyn.ipt
example_data/fast_input_files/NRELOffshrBsline5MW_Blade.dat
example_data/fast_input_files/NRELOffshrBsline5MW_Onshore.fst
example_data/fast_input_files/NRELOffshrBsline5MW_Tower_Onshore.dat
example_data/fast_input_files/TurbSim.inp
example_data/fast_input_files/AeroData/Cylinder1.dat
example_data/fast_input_files/AeroData/Cylinder2.dat
example_data/fast_input_files/AeroData/DU21_A17.dat
example_data/fast_input_files/AeroData/DU25_A17.dat
example_data/fast_input_files/AeroData/DU30_A17.dat
example_data/fast_input_files/AeroData/DU35_A17.dat
example_data/fast_input_files/AeroData/DU40_A17.dat
example_data/fast_input_files/AeroData/NACA64_A17.dat
example_data/fast_input_files/wind_files/ECD+R+2.0.wnd
example_data/fast_input_files/wind_files/ECD+R-2.0.wnd
example_data/fast_input_files/wind_files/ECD+R.wnd
example_data/fast_input_files/wind_files/ECD-R+2.0.wnd
example_data/fast_input_files/wind_files/ECD-R-2.0.wnd
example_data/fast_input_files/wind_files/ECD-R.wnd
example_data/fast_input_files/wind_files/EDC+I.wnd
example_data/fast_input_files/wind_files/EDC+O.wnd
example_data/fast_input_files/wind_files/EDC+R+2.0.wnd
example_data/fast_input_files/wind_files/EDC+R-2.0.wnd
example_data/fast_input_files/wind_files/EDC-I.wnd
example_data/fast_input_files/wind_files/EDC-O.wnd
example_data/fast_input_files/wind_files/EDC-R+2.0.wnd
spawn_wind.egg-info/PKG-INFO
spawn_wind.egg-info/SOURCES.txt
spawn_wind.egg-info/dependency_links.txt
spawn_wind.egg-info/entry_points.txt
spawn_wind.egg-info/requires.txt
spawn_wind.egg-info/top_level.txt
