Metadata-Version: 2.1
Name: spawn-wind
Version: 0.1.0
Summary: Spawn Wind is a stand-alone extension to Simmovation's Spawn package designed for the specification and execution of large simulations sets of aeroelastic calculations for wind turbines
Home-page: https://github.com/Simmovation/spawn-wind
Author: Simmovation Ltd
Author-email: info@simmovation.tech
License: GPLv3
Platform: any
Requires-Python: ==3.6.*,<4
Provides-Extra: test
Provides-Extra: publish
Provides-Extra: docs
